llamaindex_zeusdb/__init__.py
llamaindex_zeusdb-0.0.0.dist-info/METADATA
llamaindex_zeusdb-0.0.0.dist-info/WHEEL
llamaindex_zeusdb-0.0.0.dist-info/top_level.txt
llamaindex_zeusdb-0.0.0.dist-info/RECORD
