Metadata-Version: 2.4
Name: llamaindex-zeusdb
Version: 0.0.0
Summary: Advanced RAG made simple: LlamaIndex document processing + ZeusDB enterprise vector storage with production-ready performance.
